llm_cost_tracker-0.1.10.dist-info/licenses/LICENSE
tracker/__init__.py
tracker/cost_tracker.py
tracker/pricing.yaml
tracker/pricing_loader.py
tracker/utils.py
llm_cost_tracker-0.1.10.dist-info/METADATA
llm_cost_tracker-0.1.10.dist-info/WHEEL
llm_cost_tracker-0.1.10.dist-info/top_level.txt
llm_cost_tracker-0.1.10.dist-info/RECORD
