Metadata-Version: 2.4
Name: llm-cost-tracker
Version: 0.1.10
Summary: LLM API call token usage-based expense tracker
Home-page: https://github.com/hundredeuk2/TrackMyLLM
Author: Heondeuk Lee
Author-email: leehd1995@gmail.com
License: MIT
Classifier: Programming Language :: Python :: 3
Classifier: License :: OSI Approved :: MIT License
Classifier: Operating System :: OS Independent
Requires-Python: >=3.10
License-File: LICENSE
Requires-Dist: PyYAML>=5.1
Requires-Dist: tabulate>=0.9.0
Dynamic: author
Dynamic: author-email
Dynamic: classifier
Dynamic: description
Dynamic: description-content-type
Dynamic: home-page
Dynamic: license
Dynamic: license-file
Dynamic: requires-dist
Dynamic: requires-python
Dynamic: summary
